{
  "id": "179",
  "title": "Mind Mixer 12",
  "tube_capacity": 5,
  "tubes": [
    [
      "mint"
    ],
    [
      "magenta",
      "magenta",
      "magenta",
      "magenta",
      "magenta"
    ],
    [
      "purple",
      "purple",
      "purple",
      "purple"
    ],
    [
      "cyan",
      "cyan",
      "cyan",
      "cyan",
      "cyan"
    ],
    [
      "peach",
      "peach",
      "peach",
      "peach",
      "peach"
    ],
    [
      "blue",
      "blue",
      "blue",
      "blue",
      "blue"
    ],
    [
      "teal",
      "teal",
      "teal",
      "teal",
      "teal"
    ],
    [
      "mint",
      "mint",
      "mint",
      "mint"
    ],
    [
      "purple"
    ],
    [
      "indigo",
      "indigo",
      "indigo",
      "indigo",
      "indigo"
    ],
    [],
    [
      "lime",
      "lime",
      "lime",
      "lime",
      "lime"
    ],
    [
      "coral",
      "coral",
      "coral",
      "coral",
      "coral"
    ],
    [
      "yellow",
      "yellow",
      "yellow",
      "yellow",
      "yellow"
    ]
  ],
  "moves_limit": null,
  "hints": 3
}
