{
  "id": "129",
  "title": "Mind Mixer 2",
  "tube_capacity": 5,
  "tubes": [
    [
      "pink",
      "pink",
      "pink",
      "pink",
      "pink"
    ],
    [
      "lavender",
      "lavender",
      "lavender",
      "lavender",
      "lavender"
    ],
    [],
    [
      "red",
      "red",
      "red",
      "red"
    ],
    [
      "turquoise",
      "turquoise",
      "turquoise",
      "turquoise",
      "turquoise"
    ],
    [
      "teal",
      "teal",
      "teal",
      "teal",
      "teal"
    ],
    [
      "peach",
      "peach",
      "peach",
      "peach"
    ],
    [
      "peach"
    ],
    [
      "maroon",
      "maroon",
      "maroon",
      "maroon",
      "maroon"
    ],
    [
      "indigo",
      "indigo",
      "indigo",
      "indigo",
      "indigo"
    ],
    [
      "red"
    ]
  ],
  "moves_limit": null,
  "hints": 3
}
